google_image_fetcher/__init__.py
google_image_fetcher/google_image_fetcher.py
google_image_fetcher-2.0.0.dist-info/LICENSE
google_image_fetcher-2.0.0.dist-info/METADATA
google_image_fetcher-2.0.0.dist-info/WHEEL
google_image_fetcher-2.0.0.dist-info/top_level.txt
google_image_fetcher-2.0.0.dist-info/RECORD
