Metadata-Version: 2.1
Name: google-image-fetcher
Version: 2.0.0
Summary: Fetch & Download Images From Google
Author: PB2204 (Pabitra Banerjee)
Author-email: <rockstarpabitra2204@gmail.com>
Keywords: python,image,fetch,web scrapping,image scrapping
Classifier: Development Status :: 4 - Beta
Classifier: Intended Audience :: Developers
Classifier: Programming Language :: Python :: 3
Classifier: Operating System :: Unix
Classifier: Operating System :: MacOS :: MacOS X
Classifier: Operating System :: Microsoft :: Windows
License-File: LICENSE
Requires-Dist: requests
